{"name":"Alice", "dept":"Math", "age":21}
{"name":"Bob", "dept":"CS", "age":23}
{"name":"Carl", "dept":"Math", "age":25}
{"name":"Alice1", "dept":"Phy", "age":31}
{"name":"Bob1", "dept":"CS", "age":35}
{"name":"Carl1", "dept":"Math", "age":34}
{"name":"Alice2", "dept":"Math", "age":42}
{"name":"Bob2", "dept":"CHE", "age":43}
{"name":"Carl2", "dept":"Phy", "age":45}
{"name":"Alice3", "dept":"Math", "age":56}
{"name":"Bob3", "dept":"CS", "age":58}
{"name":"Carl3", "dept":"Math", "age":51}
{"name":"Alice4", "dept":"CHE", "age":16}
{"name":"Bob4", "dept":"CS", "age":13}
{"name":"Carl5", "dept":"Math", "age":15}